jsontestrunner/__init__.py
jsontestrunner/__main__.py
json_test_runner-1.0.0.dist-info/METADATA
json_test_runner-1.0.0.dist-info/WHEEL
json_test_runner-1.0.0.dist-info/entry_points.txt
json_test_runner-1.0.0.dist-info/top_level.txt
json_test_runner-1.0.0.dist-info/RECORD
