Metadata-Version: 2.1
Name: json-test-runner
Version: 1.0.0
Summary: create json report with unittest
Home-page: https://github.com/easyhutu/json-test-runner
Author: easyhutu
Author-email: 1711621009@qq.com
License: MIT
Project-URL: Documentation, https://docs.mitmproxy.org/stable/
Project-URL: Source, https://github.com/easyhutu/mitmproxy-ban/
Project-URL: Tracker, https://github.com/easyhutu/mitmproxy-ban/issues/
Keywords: json test,json test runner,report,htmltestrunner
Classifier: License :: OSI Approved :: MIT License
Classifier: Development Status :: 5 - Production/Stable
Classifier: Environment :: Console :: Curses
Classifier: Operating System :: MacOS
Classifier: Operating System :: POSIX
Classifier: Operating System :: Microsoft :: Windows
Classifier: Programming Language :: Python :: 3 :: Only
Classifier: Programming Language :: Python :: 3.9
Classifier: Programming Language :: Python :: 3.10
Classifier: Programming Language :: Python :: Implementation :: CPython
Classifier: Topic :: Security
Classifier: Topic :: Internet :: WWW/HTTP
Classifier: Topic :: Internet :: Proxy Servers
Classifier: Topic :: System :: Networking :: Monitoring
Classifier: Topic :: Software Development :: Testing
Classifier: Typing :: Typed
Requires-Python: >=3.6
